log_system/__init__.py
log_system/email_agent.py
log_system/locker_util.py
log_system/log_system_util.py
log_system-1.3.3.dist-info/METADATA
log_system-1.3.3.dist-info/WHEEL
log_system-1.3.3.dist-info/top_level.txt
log_system-1.3.3.dist-info/RECORD
